MANIFEST.in
README.rst
distribute_setup.py
setup.py
reststore/__init__.py
reststore/add_zip.py
reststore/cli.py
reststore/client.py
reststore/config.py
reststore/files.py
reststore/version.py
reststore/webapp.py
reststore.egg-info/PKG-INFO
reststore.egg-info/SOURCES.txt
reststore.egg-info/dependency_links.txt
reststore.egg-info/entry_points.txt
reststore.egg-info/not-zip-safe
reststore.egg-info/requires.txt
reststore.egg-info/top_level.txt
tests/__init__.py
tests/test_files.py